[
  {
    "dataset": "Dataset 4",
    "speed": "158 km/h",
    "target_x": -0.146,
    "target_y": 0.526,
    "target_z": -19.679,
    "mitt_x": -0.073,
    "mitt_y": 0.703,
    "mitt_z": -19.557,
    "catch_result": "Strike_PassedBall"
  },
  {
    "dataset": "Dataset 4",
    "speed": "158 km/h",
    "target_x": -0.038,
    "target_y": 0.908,
    "target_z": -19.76,
    "mitt_x": -0.072,
    "mitt_y": 0.834,
    "mitt_z": -19.602,
    "catch_result": "Strike_PassedBall"
  },
  {
    "dataset": "Dataset 4",
    "speed": "158 km/h",
    "target_x": -0.056,
    "target_y": 0.92,
    "target_z": -19.767,
    "mitt_x": -0.078,
    "mitt_y": 0.843,
    "mitt_z": -19.618,
    "catch_result": "Strike_PassedBall"
  },
  {
    "dataset": "Dataset 4",
    "speed": "158 km/h",
    "target_x": -0.044,
    "target_y": 0.923,
    "target_z": -19.792,
    "mitt_x": -0.077,
    "mitt_y": 0.698,
    "mitt_z": -19.49,
    "catch_result": "Strike_PassedBall"
  },
  {
    "dataset": "Dataset 4",
    "speed": "158 km/h",
    "target_x": -0.052,
    "target_y": 0.887,
    "target_z": -19.779,
    "mitt_x": -0.036,
    "mitt_y": 0.66,
    "mitt_z": -19.468,
    "catch_result": "Strike_PassedBall"
  },
  {
    "dataset": "Dataset 4",
    "speed": "158 km/h",
    "target_x": -0.044,
    "target_y": 0.882,
    "target_z": -19.842,
    "mitt_x": -0.083,
    "mitt_y": 0.829,
    "mitt_z": -19.631,
    "catch_result": "Strike"
  },
  {
    "dataset": "Dataset 4",
    "speed": "158 km/h",
    "target_x": -0.054,
    "target_y": 0.914,
    "target_z": -19.797,
    "mitt_x": -0.105,
    "mitt_y": 0.713,
    "mitt_z": -19.503,
    "catch_result": "Strike_PassedBall"
  },
  {
    "dataset": "Dataset 4",
    "speed": "158 km/h",
    "target_x": -0.057,
    "target_y": 0.888,
    "target_z": -19.79,
    "mitt_x": -0.095,
    "mitt_y": 0.774,
    "mitt_z": -19.581,
    "catch_result": "Strike_PassedBall"
  },
  {
    "dataset": "Dataset 4",
    "speed": "158 km/h",
    "target_x": -0.062,
    "target_y": 0.883,
    "target_z": -19.826,
    "mitt_x": -0.056,
    "mitt_y": 0.87,
    "mitt_z": -19.665,
    "catch_result": "Strike"
  },
  {
    "dataset": "Dataset 3",
    "speed": "130 km/h",
    "target_x": -0.001,
    "target_y": 0.438,
    "target_z": -19.794,
    "mitt_x": -0.058,
    "mitt_y": 0.6,
    "mitt_z": -19.733,
    "catch_result": "Ball_PassedBall"
  },
  {
    "dataset": "Dataset 3",
    "speed": "130 km/h",
    "target_x": -0.042,
    "target_y": 0.608,
    "target_z": -19.82,
    "mitt_x": 0.169,
    "mitt_y": 0.423,
    "mitt_z": -19.782,
    "catch_result": "Strike_PassedBall"
  },
  {
    "dataset": "Dataset 3",
    "speed": "130 km/h",
    "target_x": -0.051,
    "target_y": 0.676,
    "target_z": -19.829,
    "mitt_x": -0.172,
    "mitt_y": 0.479,
    "mitt_z": -19.797,
    "catch_result": "Strike_PassedBall"
  },
  {
    "dataset": "Dataset 3",
    "speed": "130 km/h",
    "target_x": -0.093,
    "target_y": 0.656,
    "target_z": -19.812,
    "mitt_x": -0.118,
    "mitt_y": 0.711,
    "mitt_z": -19.796,
    "catch_result": "Strike"
  },
  {
    "dataset": "Dataset 3",
    "speed": "130 km/h",
    "target_x": -0.075,
    "target_y": 0.606,
    "target_z": -19.808,
    "mitt_x": 0.148,
    "mitt_y": 0.562,
    "mitt_z": -19.693,
    "catch_result": "Strike"
  },
  {
    "dataset": "Dataset 3",
    "speed": "130 km/h",
    "target_x": -0.068,
    "target_y": 0.574,
    "target_z": -19.831,
    "mitt_x": -0.006,
    "mitt_y": 0.627,
    "mitt_z": -19.788,
    "catch_result": "Strike_PassedBall"
  },
  {
    "dataset": "Dataset 3",
    "speed": "130 km/h",
    "target_x": 0.027,
    "target_y": 0.734,
    "target_z": -19.865,
    "mitt_x": -0.022,
    "mitt_y": 0.364,
    "mitt_z": -19.702,
    "catch_result": "Strike_PassedBall"
  },
  {
    "dataset": "Dataset 3",
    "speed": "130 km/h",
    "target_x": -0.027,
    "target_y": 0.552,
    "target_z": -19.8,
    "mitt_x": 0.133,
    "mitt_y": 0.431,
    "mitt_z": -19.666,
    "catch_result": "Ball_PassedBall"
  },
  {
    "dataset": "Dataset 3",
    "speed": "130 km/h",
    "target_x": 0.017,
    "target_y": 0.646,
    "target_z": -19.84,
    "mitt_x": -0.005,
    "mitt_y": 0.326,
    "mitt_z": -19.717,
    "catch_result": "Strike_PassedBall"
  },
  {
    "dataset": "Dataset 3",
    "speed": "130 km/h",
    "target_x": -0.058,
    "target_y": 0.651,
    "target_z": -19.816,
    "mitt_x": -0.052,
    "mitt_y": 0.509,
    "mitt_z": -19.757,
    "catch_result": "Ball_PassedBall"
  },
  {
    "dataset": "Dataset 3",
    "speed": "130 km/h",
    "target_x": -0.084,
    "target_y": 0.621,
    "target_z": -19.831,
    "mitt_x": -0.18,
    "mitt_y": 0.618,
    "mitt_z": -19.8,
    "catch_result": "Strike_PassedBall"
  },
  {
    "dataset": "Dataset 3",
    "speed": "130 km/h",
    "target_x": -0.107,
    "target_y": 0.676,
    "target_z": -19.813,
    "mitt_x": 0.118,
    "mitt_y": 0.59,
    "mitt_z": -19.681,
    "catch_result": "Strike"
  },
  {
    "dataset": "Dataset 2",
    "speed": "130 km/h",
    "target_x": -0.087,
    "target_y": 0.904,
    "target_z": -19.739,
    "mitt_x": -0.058,
    "mitt_y": 0.809,
    "mitt_z": -19.661,
    "catch_result": "Strike_PassedBall"
  },
  {
    "dataset": "Dataset 2",
    "speed": "130 km/h",
    "target_x": 0.0,
    "target_y": 0.875,
    "target_z": -19.757,
    "mitt_x": -0.057,
    "mitt_y": 0.793,
    "mitt_z": -19.694,
    "catch_result": "Strike_PassedBall"
  },
  {
    "dataset": "Dataset 2",
    "speed": "130 km/h",
    "target_x": -0.063,
    "target_y": 1.125,
    "target_z": -19.75,
    "mitt_x": -0.037,
    "mitt_y": 1.06,
    "mitt_z": -19.724,
    "catch_result": "Strike"
  },
  {
    "dataset": "Dataset 2",
    "speed": "130 km/h",
    "target_x": -0.003,
    "target_y": 0.866,
    "target_z": -19.743,
    "mitt_x": -0.051,
    "mitt_y": 0.907,
    "mitt_z": -19.796,
    "catch_result": "Strike"
  },
  {
    "dataset": "Dataset 2",
    "speed": "130 km/h",
    "target_x": 0.095,
    "target_y": 0.868,
    "target_z": -19.771,
    "mitt_x": 0.094,
    "mitt_y": 0.827,
    "mitt_z": -19.72,
    "catch_result": "Strike"
  },
  {
    "dataset": "Dataset 2",
    "speed": "130 km/h",
    "target_x": 0.142,
    "target_y": 1.106,
    "target_z": -19.755,
    "mitt_x": 0.04,
    "mitt_y": 0.893,
    "mitt_z": -19.7,
    "catch_result": "Strike"
  },
  {
    "dataset": "Dataset 2",
    "speed": "130 km/h",
    "target_x": -0.106,
    "target_y": 1.141,
    "target_z": -19.759,
    "mitt_x": -0.114,
    "mitt_y": 1.14,
    "mitt_z": -19.757,
    "catch_result": "Ball_PassedBall"
  },
  {
    "dataset": "Dataset 2",
    "speed": "130 km/h",
    "target_x": -0.084,
    "target_y": 1.118,
    "target_z": -19.765,
    "mitt_x": -0.087,
    "mitt_y": 0.972,
    "mitt_z": -19.723,
    "catch_result": "Strike"
  },
  {
    "dataset": "Dataset 2",
    "speed": "130 km/h",
    "target_x": 0.149,
    "target_y": 0.993,
    "target_z": -19.767,
    "mitt_x": 0.056,
    "mitt_y": 0.885,
    "mitt_z": -19.75,
    "catch_result": "Strike"
  },
  {
    "dataset": "Dataset 2",
    "speed": "130 km/h",
    "target_x": -0.04,
    "target_y": 1.022,
    "target_z": -19.755,
    "mitt_x": -0.046,
    "mitt_y": 0.983,
    "mitt_z": -19.75,
    "catch_result": "Strike"
  },
  {
    "dataset": "Dataset 2",
    "speed": "130 km/h",
    "target_x": 0.006,
    "target_y": 0.844,
    "target_z": -19.771,
    "mitt_x": -0.032,
    "mitt_y": 0.887,
    "mitt_z": -19.772,
    "catch_result": "Strike"
  },
  {
    "dataset": "Dataset 2",
    "speed": "130 km/h",
    "target_x": -0.144,
    "target_y": 1.03,
    "target_z": -19.77,
    "mitt_x": -0.089,
    "mitt_y": 1.032,
    "mitt_z": -19.77,
    "catch_result": "Strike"
  },
  {
    "dataset": "Dataset 2",
    "speed": "130 km/h",
    "target_x": -0.077,
    "target_y": 0.905,
    "target_z": -19.772,
    "mitt_x": -0.058,
    "mitt_y": 0.905,
    "mitt_z": -19.763,
    "catch_result": "Strike"
  },
  {
    "dataset": "Dataset 2",
    "speed": "130 km/h",
    "target_x": 0.01,
    "target_y": 0.873,
    "target_z": -19.78,
    "mitt_x": 0.101,
    "mitt_y": 0.849,
    "mitt_z": -19.754,
    "catch_result": "Strike_PassedBall"
  },
  {
    "dataset": "Dataset 2",
    "speed": "130 km/h",
    "target_x": 0.001,
    "target_y": 0.88,
    "target_z": -19.773,
    "mitt_x": -0.055,
    "mitt_y": 0.919,
    "mitt_z": -19.776,
    "catch_result": "Strike"
  },
  {
    "dataset": "Dataset 2",
    "speed": "130 km/h",
    "target_x": 0.147,
    "target_y": 0.915,
    "target_z": -19.779,
    "mitt_x": 0.135,
    "mitt_y": 0.896,
    "mitt_z": -19.766,
    "catch_result": "Strike_PassedBall"
  },
  {
    "dataset": "Dataset 2",
    "speed": "130 km/h",
    "target_x": 0.106,
    "target_y": 0.879,
    "target_z": -19.77,
    "mitt_x": -0.006,
    "mitt_y": 0.872,
    "mitt_z": -19.764,
    "catch_result": "Strike"
  },
  {
    "dataset": "Dataset 2",
    "speed": "130 km/h",
    "target_x": 0.091,
    "target_y": 0.858,
    "target_z": -19.783,
    "mitt_x": 0.014,
    "mitt_y": 0.856,
    "mitt_z": -19.774,
    "catch_result": "Strike"
  },
  {
    "dataset": "Dataset 2",
    "speed": "130 km/h",
    "target_x": -0.032,
    "target_y": 1.135,
    "target_z": -19.765,
    "mitt_x": -0.036,
    "mitt_y": 1.077,
    "mitt_z": -19.748,
    "catch_result": "Strike"
  },
  {
    "dataset": "Dataset 0",
    "speed": "130 km/h",
    "target_x": -0.019,
    "target_y": 1.033,
    "target_z": -19.796,
    "mitt_x": 0.247,
    "mitt_y": 1.153,
    "mitt_z": -19.677,
    "catch_result": "Strike"
  },
  {
    "dataset": "Dataset 0",
    "speed": "130 km/h",
    "target_x": -0.003,
    "target_y": 1.043,
    "target_z": -19.656,
    "mitt_x": -0.164,
    "mitt_y": 1.03,
    "mitt_z": -19.692,
    "catch_result": "Strike"
  },
  {
    "dataset": "Dataset 0",
    "speed": "130 km/h",
    "target_x": -0.011,
    "target_y": 1.007,
    "target_z": -19.653,
    "mitt_x": 0.051,
    "mitt_y": 1.003,
    "mitt_z": -19.654,
    "catch_result": "Strike"
  },
  {
    "dataset": "Dataset 0",
    "speed": "130 km/h",
    "target_x": 0.0,
    "target_y": 1.016,
    "target_z": -19.723,
    "mitt_x": 0.137,
    "mitt_y": 1.002,
    "mitt_z": -19.644,
    "catch_result": "Strike"
  },
  {
    "dataset": "Dataset 0",
    "speed": "130 km/h",
    "target_x": -0.134,
    "target_y": 0.979,
    "target_z": -19.726,
    "mitt_x": -0.482,
    "mitt_y": 1.069,
    "mitt_z": -19.841,
    "catch_result": "Ball_PassedBall"
  },
  {
    "dataset": "Dataset 0",
    "speed": "130 km/h",
    "target_x": -0.001,
    "target_y": 0.986,
    "target_z": -19.673,
    "mitt_x": -0.262,
    "mitt_y": 0.957,
    "mitt_z": -19.693,
    "catch_result": "Strike"
  },
  {
    "dataset": "Dataset 0",
    "speed": "130 km/h",
    "target_x": -0.01,
    "target_y": 1.002,
    "target_z": -19.672,
    "mitt_x": 0.079,
    "mitt_y": 0.989,
    "mitt_z": -19.671,
    "catch_result": "Strike"
  },
  {
    "dataset": "Dataset 0",
    "speed": "130 km/h",
    "target_x": -0.071,
    "target_y": 1.031,
    "target_z": -19.693,
    "mitt_x": 0.047,
    "mitt_y": 0.943,
    "mitt_z": -19.698,
    "catch_result": "Strike"
  },
  {
    "dataset": "Dataset 0",
    "speed": "130 km/h",
    "target_x": -0.149,
    "target_y": 0.985,
    "target_z": -19.785,
    "mitt_x": -0.228,
    "mitt_y": 0.814,
    "mitt_z": -19.746,
    "catch_result": "Strike"
  },
  {
    "dataset": "Dataset 0",
    "speed": "130 km/h",
    "target_x": 0.004,
    "target_y": 1.093,
    "target_z": -19.75,
    "mitt_x": -0.382,
    "mitt_y": 0.929,
    "mitt_z": -19.896,
    "catch_result": "Strike_PassedBall"
  },
  {
    "dataset": "Dataset 0",
    "speed": "130 km/h",
    "target_x": 0.0,
    "target_y": 1.074,
    "target_z": -19.714,
    "mitt_x": -0.152,
    "mitt_y": 1.113,
    "mitt_z": -19.694,
    "catch_result": "Strike"
  },
  {
    "dataset": "Dataset 0",
    "speed": "130 km/h",
    "target_x": 0.025,
    "target_y": 1.084,
    "target_z": -19.727,
    "mitt_x": -0.206,
    "mitt_y": 0.985,
    "mitt_z": -19.729,
    "catch_result": "Strike"
  },
  {
    "dataset": "Dataset 0",
    "speed": "130 km/h",
    "target_x": 0.005,
    "target_y": 1.054,
    "target_z": -19.703,
    "mitt_x": -0.135,
    "mitt_y": 0.881,
    "mitt_z": -19.766,
    "catch_result": "Strike"
  },
  {
    "dataset": "Dataset 0",
    "speed": "130 km/h",
    "target_x": 0.002,
    "target_y": 1.059,
    "target_z": -19.694,
    "mitt_x": -0.161,
    "mitt_y": 1.089,
    "mitt_z": -19.718,
    "catch_result": "Strike"
  },
  {
    "dataset": "Dataset 0",
    "speed": "130 km/h",
    "target_x": -0.019,
    "target_y": 1.01,
    "target_z": -19.753,
    "mitt_x": -0.157,
    "mitt_y": 1.035,
    "mitt_z": -19.696,
    "catch_result": "Strike"
  },
  {
    "dataset": "Dataset 0",
    "speed": "130 km/h",
    "target_x": 0.001,
    "target_y": 1.044,
    "target_z": -19.703,
    "mitt_x": 0.152,
    "mitt_y": 1.038,
    "mitt_z": -19.639,
    "catch_result": "Strike"
  },
  {
    "dataset": "Dataset 0",
    "speed": "130 km/h",
    "target_x": -0.039,
    "target_y": 1.057,
    "target_z": -19.678,
    "mitt_x": -0.241,
    "mitt_y": 1.066,
    "mitt_z": -19.693,
    "catch_result": "Strike"
  },
  {
    "dataset": "Dataset 0",
    "speed": "130 km/h",
    "target_x": 0.002,
    "target_y": 1.013,
    "target_z": -19.728,
    "mitt_x": -0.215,
    "mitt_y": 0.948,
    "mitt_z": -19.719,
    "catch_result": "Strike"
  },
  {
    "dataset": "Dataset 0",
    "speed": "130 km/h",
    "target_x": 0.017,
    "target_y": 0.971,
    "target_z": -19.717,
    "mitt_x": -0.19,
    "mitt_y": 0.95,
    "mitt_z": -19.72,
    "catch_result": "Strike"
  },
  {
    "dataset": "Dataset 4",
    "speed": "100 km/h",
    "target_x": -0.068,
    "target_y": 0.858,
    "target_z": -19.75,
    "mitt_x": -0.032,
    "mitt_y": 0.876,
    "mitt_z": -19.615,
    "catch_result": "Strike"
  },
  {
    "dataset": "Dataset 4",
    "speed": "100 km/h",
    "target_x": -0.075,
    "target_y": 0.894,
    "target_z": -19.729,
    "mitt_x": -0.081,
    "mitt_y": 0.711,
    "mitt_z": -19.519,
    "catch_result": "Strike_PassedBall"
  },
  {
    "dataset": "Dataset 4",
    "speed": "100 km/h",
    "target_x": -0.077,
    "target_y": 0.88,
    "target_z": -19.721,
    "mitt_x": 0.014,
    "mitt_y": 0.9,
    "mitt_z": -19.566,
    "catch_result": "Strike"
  },
  {
    "dataset": "Dataset 4",
    "speed": "100 km/h",
    "target_x": -0.078,
    "target_y": 0.865,
    "target_z": -19.741,
    "mitt_x": -0.066,
    "mitt_y": 0.835,
    "mitt_z": -19.68,
    "catch_result": "Strike_PassedBall"
  },
  {
    "dataset": "Dataset 4",
    "speed": "100 km/h",
    "target_x": -0.08,
    "target_y": 0.858,
    "target_z": -19.73,
    "mitt_x": 0.043,
    "mitt_y": 0.704,
    "mitt_z": -19.495,
    "catch_result": "Strike_PassedBall"
  },
  {
    "dataset": "Dataset 4",
    "speed": "100 km/h",
    "target_x": -0.051,
    "target_y": 0.866,
    "target_z": -19.774,
    "mitt_x": -0.095,
    "mitt_y": 0.946,
    "mitt_z": -19.59,
    "catch_result": "Strike"
  },
  {
    "dataset": "Dataset 4",
    "speed": "100 km/h",
    "target_x": -0.055,
    "target_y": 0.897,
    "target_z": -19.769,
    "mitt_x": 0.002,
    "mitt_y": 0.766,
    "mitt_z": -19.479,
    "catch_result": "Strike_PassedBall"
  },
  {
    "dataset": "Dataset 4",
    "speed": "100 km/h",
    "target_x": -0.056,
    "target_y": 0.89,
    "target_z": -19.77,
    "mitt_x": -0.294,
    "mitt_y": 0.764,
    "mitt_z": -19.503,
    "catch_result": "Strike_PassedBall"
  },
  {
    "dataset": "Dataset 4",
    "speed": "100 km/h",
    "target_x": -0.058,
    "target_y": 0.888,
    "target_z": -19.764,
    "mitt_x": -0.021,
    "mitt_y": 0.698,
    "mitt_z": -19.435,
    "catch_result": "Strike_PassedBall"
  },
  {
    "dataset": "Dataset 1",
    "speed": "130 km/h",
    "target_x": -0.062,
    "target_y": 0.696,
    "target_z": -19.686,
    "mitt_x": -0.039,
    "mitt_y": 0.798,
    "mitt_z": -19.519,
    "catch_result": "Strike_PassedBall"
  },
  {
    "dataset": "Dataset 1",
    "speed": "130 km/h",
    "target_x": -0.028,
    "target_y": 0.852,
    "target_z": -19.564,
    "mitt_x": 0.011,
    "mitt_y": 0.767,
    "mitt_z": -19.54,
    "catch_result": "Strike"
  },
  {
    "dataset": "Dataset 1",
    "speed": "130 km/h",
    "target_x": -0.023,
    "target_y": 0.851,
    "target_z": -19.567,
    "mitt_x": 0.003,
    "mitt_y": 0.799,
    "mitt_z": -19.543,
    "catch_result": "Strike"
  },
  {
    "dataset": "Dataset 1",
    "speed": "130 km/h",
    "target_x": -0.023,
    "target_y": 0.841,
    "target_z": -19.568,
    "mitt_x": -0.012,
    "mitt_y": 0.76,
    "mitt_z": -19.542,
    "catch_result": "Strike"
  },
  {
    "dataset": "Dataset 1",
    "speed": "130 km/h",
    "target_x": -0.026,
    "target_y": 0.836,
    "target_z": -19.564,
    "mitt_x": -0.024,
    "mitt_y": 0.849,
    "mitt_z": -19.544,
    "catch_result": "Strike"
  },
  {
    "dataset": "Dataset 1",
    "speed": "130 km/h",
    "target_x": -0.036,
    "target_y": 0.832,
    "target_z": -19.563,
    "mitt_x": -0.102,
    "mitt_y": 0.826,
    "mitt_z": -19.556,
    "catch_result": "Strike"
  },
  {
    "dataset": "Dataset 1",
    "speed": "130 km/h",
    "target_x": -0.051,
    "target_y": 0.833,
    "target_z": -19.568,
    "mitt_x": 0.059,
    "mitt_y": 0.778,
    "mitt_z": -19.532,
    "catch_result": "Strike"
  },
  {
    "dataset": "Dataset 1",
    "speed": "130 km/h",
    "target_x": -0.034,
    "target_y": 0.837,
    "target_z": -19.565,
    "mitt_x": -0.238,
    "mitt_y": 1.075,
    "mitt_z": -19.587,
    "catch_result": "Ball_WildPitch"
  },
  {
    "dataset": "Dataset 1",
    "speed": "130 km/h",
    "target_x": -0.093,
    "target_y": 0.866,
    "target_z": -19.586,
    "mitt_x": 0.002,
    "mitt_y": 0.877,
    "mitt_z": -19.524,
    "catch_result": "Strike"
  },
  {
    "dataset": "Dataset 1",
    "speed": "130 km/h",
    "target_x": -0.061,
    "target_y": 0.857,
    "target_z": -19.568,
    "mitt_x": -0.06,
    "mitt_y": 0.826,
    "mitt_z": -19.558,
    "catch_result": "Strike_PassedBall"
  },
  {
    "dataset": "Dataset 3",
    "speed": "158 km/h",
    "target_x": -0.001,
    "target_y": 0.448,
    "target_z": -19.792,
    "mitt_x": 0.086,
    "mitt_y": 0.412,
    "mitt_z": -19.735,
    "catch_result": "Ball_PassedBall"
  },
  {
    "dataset": "Dataset 3",
    "speed": "158 km/h",
    "target_x": 0.003,
    "target_y": 0.466,
    "target_z": -19.789,
    "mitt_x": 0.13,
    "mitt_y": 0.529,
    "mitt_z": -19.66,
    "catch_result": "Strike"
  },
  {
    "dataset": "Dataset 3",
    "speed": "158 km/h",
    "target_x": -0.013,
    "target_y": 0.555,
    "target_z": -19.831,
    "mitt_x": -0.007,
    "mitt_y": 0.464,
    "mitt_z": -19.663,
    "catch_result": "Ball_PassedBall"
  },
  {
    "dataset": "Dataset 3",
    "speed": "158 km/h",
    "target_x": -0.051,
    "target_y": 0.575,
    "target_z": -19.78,
    "mitt_x": -0.065,
    "mitt_y": 0.563,
    "mitt_z": -19.717,
    "catch_result": "Strike"
  },
  {
    "dataset": "Dataset 3",
    "speed": "158 km/h",
    "target_x": -0.025,
    "target_y": 0.615,
    "target_z": -19.817,
    "mitt_x": -0.008,
    "mitt_y": 0.416,
    "mitt_z": -19.663,
    "catch_result": "Ball"
  },
  {
    "dataset": "Dataset 3",
    "speed": "158 km/h",
    "target_x": -0.065,
    "target_y": 0.45,
    "target_z": -19.736,
    "mitt_x": -0.026,
    "mitt_y": 0.298,
    "mitt_z": -19.634,
    "catch_result": "Ball"
  },
  {
    "dataset": "Dataset 3",
    "speed": "158 km/h",
    "target_x": -0.065,
    "target_y": 0.464,
    "target_z": -19.757,
    "mitt_x": -0.028,
    "mitt_y": 0.641,
    "mitt_z": -19.763,
    "catch_result": "Strike_PassedBall"
  },
  {
    "dataset": "Dataset 3",
    "speed": "158 km/h",
    "target_x": -0.046,
    "target_y": 0.65,
    "target_z": -19.789,
    "mitt_x": -0.054,
    "mitt_y": 0.475,
    "mitt_z": -19.738,
    "catch_result": "Strike_PassedBall"
  },
  {
    "dataset": "Dataset 3",
    "speed": "158 km/h",
    "target_x": -0.017,
    "target_y": 0.687,
    "target_z": -19.842,
    "mitt_x": 0.093,
    "mitt_y": 0.737,
    "mitt_z": -19.896,
    "catch_result": "Strike_PassedBall"
  },
  {
    "dataset": "Dataset 3",
    "speed": "158 km/h",
    "target_x": 0.11,
    "target_y": 0.687,
    "target_z": -19.915,
    "mitt_x": 0.157,
    "mitt_y": 0.363,
    "mitt_z": -19.674,
    "catch_result": "Strike_PassedBall"
  },
  {
    "dataset": "Dataset 3",
    "speed": "158 km/h",
    "target_x": -0.044,
    "target_y": 0.62,
    "target_z": -19.807,
    "mitt_x": 0.007,
    "mitt_y": 0.54,
    "mitt_z": -19.675,
    "catch_result": "Ball"
  },
  {
    "dataset": "Dataset 3",
    "speed": "158 km/h",
    "target_x": -0.06,
    "target_y": 0.657,
    "target_z": -19.799,
    "mitt_x": -0.083,
    "mitt_y": 0.49,
    "mitt_z": -19.674,
    "catch_result": "Ball_PassedBall"
  },
  {
    "dataset": "Dataset 3",
    "speed": "158 km/h",
    "target_x": -0.019,
    "target_y": 0.664,
    "target_z": -19.805,
    "mitt_x": 0.184,
    "mitt_y": 0.612,
    "mitt_z": -19.737,
    "catch_result": "Strike"
  },
  {
    "dataset": "Dataset 3",
    "speed": "158 km/h",
    "target_x": -0.074,
    "target_y": 0.455,
    "target_z": -19.753,
    "mitt_x": 0.119,
    "mitt_y": 0.536,
    "mitt_z": -19.641,
    "catch_result": "Ball"
  },
  {
    "dataset": "Dataset 3",
    "speed": "158 km/h",
    "target_x": -0.05,
    "target_y": 0.695,
    "target_z": -19.751,
    "mitt_x": -0.026,
    "mitt_y": 0.508,
    "mitt_z": -19.65,
    "catch_result": "Ball"
  },
  {
    "dataset": "Dataset 3",
    "speed": "158 km/h",
    "target_x": -0.022,
    "target_y": 0.636,
    "target_z": -19.782,
    "mitt_x": -0.039,
    "mitt_y": 0.742,
    "mitt_z": -19.843,
    "catch_result": "Strike_PassedBall"
  },
  {
    "dataset": "Dataset 3",
    "speed": "158 km/h",
    "target_x": -0.034,
    "target_y": 0.734,
    "target_z": -19.843,
    "mitt_x": -0.056,
    "mitt_y": 0.624,
    "mitt_z": -19.706,
    "catch_result": "Strike_PassedBall"
  },
  {
    "dataset": "Dataset 3",
    "speed": "158 km/h",
    "target_x": -0.086,
    "target_y": 0.698,
    "target_z": -19.818,
    "mitt_x": -0.205,
    "mitt_y": 0.704,
    "mitt_z": -19.75,
    "catch_result": "Ball_PassedBall"
  },
  {
    "dataset": "Dataset 3",
    "speed": "158 km/h",
    "target_x": -0.055,
    "target_y": 0.669,
    "target_z": -19.784,
    "mitt_x": -0.188,
    "mitt_y": 0.708,
    "mitt_z": -19.755,
    "catch_result": "Strike"
  },
  {
    "dataset": "Dataset 3",
    "speed": "158 km/h",
    "target_x": -0.055,
    "target_y": 0.713,
    "target_z": -19.841,
    "mitt_x": -0.134,
    "mitt_y": 0.688,
    "mitt_z": -19.756,
    "catch_result": "Strike_PassedBall"
  },
  {
    "dataset": "Dataset 3",
    "speed": "158 km/h",
    "target_x": -0.103,
    "target_y": 0.661,
    "target_z": -19.826,
    "mitt_x": -0.305,
    "mitt_y": 0.704,
    "mitt_z": -19.738,
    "catch_result": "Strike"
  },
  {
    "dataset": "Dataset 3",
    "speed": "158 km/h",
    "target_x": -0.088,
    "target_y": 0.634,
    "target_z": -19.792,
    "mitt_x": 0.074,
    "mitt_y": 0.573,
    "mitt_z": -19.683,
    "catch_result": "Ball_PassedBall"
  },
  {
    "dataset": "Dataset 3",
    "speed": "158 km/h",
    "target_x": 0.022,
    "target_y": 0.714,
    "target_z": -19.867,
    "mitt_x": 0.236,
    "mitt_y": 0.775,
    "mitt_z": -20.002,
    "catch_result": "Strike_PassedBall"
  },
  {
    "dataset": "Dataset 4",
    "speed": "130 km/h",
    "target_x": -0.041,
    "target_y": 0.917,
    "target_z": -19.681,
    "mitt_x": -0.261,
    "mitt_y": 0.731,
    "mitt_z": -19.482,
    "catch_result": "Strike_PassedBall"
  },
  {
    "dataset": "Dataset 4",
    "speed": "130 km/h",
    "target_x": -0.083,
    "target_y": 0.875,
    "target_z": -19.724,
    "mitt_x": -0.127,
    "mitt_y": 0.828,
    "mitt_z": -19.578,
    "catch_result": "Strike"
  },
  {
    "dataset": "Dataset 4",
    "speed": "130 km/h",
    "target_x": -0.08,
    "target_y": 0.881,
    "target_z": -19.771,
    "mitt_x": -0.077,
    "mitt_y": 0.876,
    "mitt_z": -19.771,
    "catch_result": "Strike_PassedBall"
  },
  {
    "dataset": "Dataset 4",
    "speed": "130 km/h",
    "target_x": -0.083,
    "target_y": 0.867,
    "target_z": -19.773,
    "mitt_x": -0.035,
    "mitt_y": 0.857,
    "mitt_z": -19.72,
    "catch_result": "Strike_PassedBall"
  },
  {
    "dataset": "Dataset 4",
    "speed": "130 km/h",
    "target_x": -0.037,
    "target_y": 0.863,
    "target_z": -19.767,
    "mitt_x": -0.096,
    "mitt_y": 0.744,
    "mitt_z": -19.532,
    "catch_result": "Strike_PassedBall"
  },
  {
    "dataset": "Dataset 4",
    "speed": "130 km/h",
    "target_x": -0.048,
    "target_y": 0.861,
    "target_z": -19.784,
    "mitt_x": -0.095,
    "mitt_y": 0.813,
    "mitt_z": -19.712,
    "catch_result": "Strike_PassedBall"
  },
  {
    "dataset": "Dataset 4",
    "speed": "130 km/h",
    "target_x": -0.067,
    "target_y": 0.858,
    "target_z": -19.789,
    "mitt_x": -0.154,
    "mitt_y": 0.689,
    "mitt_z": -19.555,
    "catch_result": "Strike_PassedBall"
  },
  {
    "dataset": "Dataset 4",
    "speed": "130 km/h",
    "target_x": -0.073,
    "target_y": 0.874,
    "target_z": -19.798,
    "mitt_x": -0.084,
    "mitt_y": 0.803,
    "mitt_z": -19.611,
    "catch_result": "Strike"
  },
  {
    "dataset": "Dataset 4",
    "speed": "130 km/h",
    "target_x": -0.074,
    "target_y": 0.878,
    "target_z": -19.814,
    "mitt_x": 0.037,
    "mitt_y": 0.91,
    "mitt_z": -19.613,
    "catch_result": "Strike"
  },
  {
    "dataset": "Dataset 1",
    "speed": "100 km/h",
    "target_x": -0.057,
    "target_y": 0.844,
    "target_z": -19.602,
    "mitt_x": -0.065,
    "mitt_y": 0.765,
    "mitt_z": -19.569,
    "catch_result": "Ball_PassedBall"
  },
  {
    "dataset": "Dataset 1",
    "speed": "100 km/h",
    "target_x": -0.046,
    "target_y": 0.823,
    "target_z": -19.598,
    "mitt_x": -0.126,
    "mitt_y": 0.742,
    "mitt_z": -19.495,
    "catch_result": "Strike_PassedBall"
  },
  {
    "dataset": "Dataset 1",
    "speed": "100 km/h",
    "target_x": -0.054,
    "target_y": 0.833,
    "target_z": -19.587,
    "mitt_x": 0.064,
    "mitt_y": 0.764,
    "mitt_z": -19.561,
    "catch_result": "Strike"
  },
  {
    "dataset": "Dataset 1",
    "speed": "100 km/h",
    "target_x": -0.043,
    "target_y": 0.812,
    "target_z": -19.589,
    "mitt_x": 0.012,
    "mitt_y": 0.781,
    "mitt_z": -19.575,
    "catch_result": "Strike_PassedBall"
  },
  {
    "dataset": "Dataset 1",
    "speed": "100 km/h",
    "target_x": -0.044,
    "target_y": 0.816,
    "target_z": -19.598,
    "mitt_x": -0.195,
    "mitt_y": 0.775,
    "mitt_z": -19.542,
    "catch_result": "Strike"
  },
  {
    "dataset": "Dataset 1",
    "speed": "100 km/h",
    "target_x": -0.056,
    "target_y": 0.827,
    "target_z": -19.619,
    "mitt_x": -0.153,
    "mitt_y": 0.865,
    "mitt_z": -19.565,
    "catch_result": "Strike_PassedBall"
  },
  {
    "dataset": "Dataset 1",
    "speed": "100 km/h",
    "target_x": -0.069,
    "target_y": 0.815,
    "target_z": -19.615,
    "mitt_x": -0.038,
    "mitt_y": 0.841,
    "mitt_z": -19.59,
    "catch_result": "Strike"
  },
  {
    "dataset": "Dataset 1",
    "speed": "100 km/h",
    "target_x": -0.051,
    "target_y": 0.82,
    "target_z": -19.627,
    "mitt_x": -0.119,
    "mitt_y": 0.794,
    "mitt_z": -19.526,
    "catch_result": "Strike"
  },
  {
    "dataset": "Dataset 1",
    "speed": "100 km/h",
    "target_x": -0.064,
    "target_y": 0.807,
    "target_z": -19.611,
    "mitt_x": 0.083,
    "mitt_y": 0.853,
    "mitt_z": -19.58,
    "catch_result": "Strike_PassedBall"
  },
  {
    "dataset": "Dataset 1",
    "speed": "100 km/h",
    "target_x": -0.034,
    "target_y": 0.788,
    "target_z": -19.621,
    "mitt_x": 0.01,
    "mitt_y": 0.843,
    "mitt_z": -19.594,
    "catch_result": "Strike"
  },
  {
    "dataset": "Dataset 2",
    "speed": "158 km/h",
    "target_x": 0.0,
    "target_y": 0.88,
    "target_z": -19.816,
    "mitt_x": 0.038,
    "mitt_y": 0.808,
    "mitt_z": -19.745,
    "catch_result": "Strike"
  },
  {
    "dataset": "Dataset 2",
    "speed": "158 km/h",
    "target_x": -0.011,
    "target_y": 0.864,
    "target_z": -19.806,
    "mitt_x": -0.053,
    "mitt_y": 0.849,
    "mitt_z": -19.773,
    "catch_result": "Ball_PassedBall"
  },
  {
    "dataset": "Dataset 2",
    "speed": "158 km/h",
    "target_x": -0.05,
    "target_y": 1.168,
    "target_z": -19.778,
    "mitt_x": -0.03,
    "mitt_y": 1.092,
    "mitt_z": -19.757,
    "catch_result": "Strike_PassedBall"
  },
  {
    "dataset": "Dataset 2",
    "speed": "158 km/h",
    "target_x": -0.037,
    "target_y": 1.165,
    "target_z": -19.787,
    "mitt_x": -0.039,
    "mitt_y": 1.156,
    "mitt_z": -19.784,
    "catch_result": "Strike_PassedBall"
  },
  {
    "dataset": "Dataset 2",
    "speed": "158 km/h",
    "target_x": -0.117,
    "target_y": 1.179,
    "target_z": -19.783,
    "mitt_x": -0.077,
    "mitt_y": 1.172,
    "mitt_z": -19.764,
    "catch_result": "Strike"
  },
  {
    "dataset": "Dataset 2",
    "speed": "158 km/h",
    "target_x": -0.067,
    "target_y": 0.863,
    "target_z": -19.783,
    "mitt_x": -0.052,
    "mitt_y": 0.857,
    "mitt_z": -19.77,
    "catch_result": "Strike_PassedBall"
  },
  {
    "dataset": "Dataset 2",
    "speed": "158 km/h",
    "target_x": -0.081,
    "target_y": 0.893,
    "target_z": -19.796,
    "mitt_x": -0.052,
    "mitt_y": 0.85,
    "mitt_z": -19.749,
    "catch_result": "Strike_PassedBall"
  },
  {
    "dataset": "Dataset 2",
    "speed": "158 km/h",
    "target_x": -0.074,
    "target_y": 0.914,
    "target_z": -19.771,
    "mitt_x": -0.095,
    "mitt_y": 0.854,
    "mitt_z": -19.735,
    "catch_result": "Ball_PassedBall"
  },
  {
    "dataset": "Dataset 2",
    "speed": "158 km/h",
    "target_x": -0.039,
    "target_y": 0.871,
    "target_z": -19.78,
    "mitt_x": -0.026,
    "mitt_y": 0.858,
    "mitt_z": -19.765,
    "catch_result": "Strike"
  },
  {
    "dataset": "Dataset 2",
    "speed": "158 km/h",
    "target_x": 0.1,
    "target_y": 0.867,
    "target_z": -19.788,
    "mitt_x": -0.015,
    "mitt_y": 0.833,
    "mitt_z": -19.759,
    "catch_result": "Strike"
  },
  {
    "dataset": "Dataset 2",
    "speed": "158 km/h",
    "target_x": 0.08,
    "target_y": 0.867,
    "target_z": -19.781,
    "mitt_x": -0.006,
    "mitt_y": 0.83,
    "mitt_z": -19.754,
    "catch_result": "Strike_PassedBall"
  },
  {
    "dataset": "Dataset 0",
    "speed": "100 km/h",
    "target_x": 0.001,
    "target_y": 1.076,
    "target_z": -19.702,
    "mitt_x": 0.031,
    "mitt_y": 1.266,
    "mitt_z": -19.67,
    "catch_result": "Strike"
  },
  {
    "dataset": "Dataset 0",
    "speed": "100 km/h",
    "target_x": -0.026,
    "target_y": 1.083,
    "target_z": -19.802,
    "mitt_x": -0.237,
    "mitt_y": 1.067,
    "mitt_z": -19.766,
    "catch_result": "Strike"
  },
  {
    "dataset": "Dataset 0",
    "speed": "100 km/h",
    "target_x": -0.014,
    "target_y": 1.086,
    "target_z": -19.793,
    "mitt_x": -0.069,
    "mitt_y": 1.18,
    "mitt_z": -19.839,
    "catch_result": "Strike"
  },
  {
    "dataset": "Dataset 0",
    "speed": "100 km/h",
    "target_x": 0.01,
    "target_y": 1.087,
    "target_z": -19.838,
    "mitt_x": 0.034,
    "mitt_y": 1.288,
    "mitt_z": -19.793,
    "catch_result": "Ball_PassedBall"
  },
  {
    "dataset": "Dataset 0",
    "speed": "100 km/h",
    "target_x": -0.004,
    "target_y": 1.068,
    "target_z": -19.79,
    "mitt_x": -0.237,
    "mitt_y": 1.219,
    "mitt_z": -19.805,
    "catch_result": "Strike"
  },
  {
    "dataset": "Dataset 0",
    "speed": "100 km/h",
    "target_x": -0.003,
    "target_y": 1.112,
    "target_z": -19.825,
    "mitt_x": -0.176,
    "mitt_y": 1.374,
    "mitt_z": -19.766,
    "catch_result": "Strike"
  },
  {
    "dataset": "Dataset 0",
    "speed": "100 km/h",
    "target_x": -0.014,
    "target_y": 1.036,
    "target_z": -19.798,
    "mitt_x": -0.246,
    "mitt_y": 1.12,
    "mitt_z": -19.801,
    "catch_result": "Strike"
  },
  {
    "dataset": "Dataset 0",
    "speed": "100 km/h",
    "target_x": 0.003,
    "target_y": 1.031,
    "target_z": -19.778,
    "mitt_x": -0.018,
    "mitt_y": 1.22,
    "mitt_z": -19.659,
    "catch_result": "Strike"
  },
  {
    "dataset": "Dataset 0",
    "speed": "100 km/h",
    "target_x": 0.005,
    "target_y": 1.022,
    "target_z": -19.734,
    "mitt_x": 0.123,
    "mitt_y": 0.976,
    "mitt_z": -19.695,
    "catch_result": "Strike"
  },
  {
    "dataset": "Dataset 0",
    "speed": "100 km/h",
    "target_x": 0.02,
    "target_y": 1.04,
    "target_z": -19.721,
    "mitt_x": 0.037,
    "mitt_y": 1.301,
    "mitt_z": -19.681,
    "catch_result": "Strike"
  },
  {
    "dataset": "Dataset 0",
    "speed": "100 km/h",
    "target_x": -0.001,
    "target_y": 1.041,
    "target_z": -19.733,
    "mitt_x": -0.084,
    "mitt_y": 1.333,
    "mitt_z": -19.758,
    "catch_result": "Strike"
  },
  {
    "dataset": "Dataset 0",
    "speed": "100 km/h",
    "target_x": 0.017,
    "target_y": 0.981,
    "target_z": -19.744,
    "mitt_x": 0.141,
    "mitt_y": 1.208,
    "mitt_z": -19.737,
    "catch_result": "Strike_PassedBall"
  },
  {
    "dataset": "Dataset 0",
    "speed": "100 km/h",
    "target_x": 0.005,
    "target_y": 0.992,
    "target_z": -19.751,
    "mitt_x": -0.165,
    "mitt_y": 0.988,
    "mitt_z": -19.771,
    "catch_result": "Strike"
  },
  {
    "dataset": "Dataset 0",
    "speed": "100 km/h",
    "target_x": 0.009,
    "target_y": 1.022,
    "target_z": -19.744,
    "mitt_x": 0.014,
    "mitt_y": 1.017,
    "mitt_z": -19.73,
    "catch_result": "Strike"
  },
  {
    "dataset": "Dataset 0",
    "speed": "100 km/h",
    "target_x": 0.012,
    "target_y": 1.018,
    "target_z": -19.776,
    "mitt_x": 0.228,
    "mitt_y": 1.069,
    "mitt_z": -19.699,
    "catch_result": "Strike"
  },
  {
    "dataset": "Dataset 0",
    "speed": "100 km/h",
    "target_x": -0.091,
    "target_y": 1.002,
    "target_z": -19.786,
    "mitt_x": -0.018,
    "mitt_y": 0.895,
    "mitt_z": -19.781,
    "catch_result": "Strike"
  },
  {
    "dataset": "Dataset 0",
    "speed": "100 km/h",
    "target_x": 0.008,
    "target_y": 1.042,
    "target_z": -19.816,
    "mitt_x": -0.29,
    "mitt_y": 0.954,
    "mitt_z": -19.794,
    "catch_result": "Strike"
  },
  {
    "dataset": "Dataset 0",
    "speed": "100 km/h",
    "target_x": -0.005,
    "target_y": 1.033,
    "target_z": -19.817,
    "mitt_x": -0.278,
    "mitt_y": 1.035,
    "mitt_z": -19.806,
    "catch_result": "Strike"
  },
  {
    "dataset": "Dataset 0",
    "speed": "100 km/h",
    "target_x": 0.02,
    "target_y": 1.011,
    "target_z": -19.737,
    "mitt_x": 0.023,
    "mitt_y": 0.907,
    "mitt_z": -19.693,
    "catch_result": "Strike"
  },
  {
    "dataset": "Dataset 0",
    "speed": "100 km/h",
    "target_x": 0.012,
    "target_y": 0.94,
    "target_z": -19.755,
    "mitt_x": -0.235,
    "mitt_y": 0.758,
    "mitt_z": -19.736,
    "catch_result": "Strike"
  },
  {
    "dataset": "Dataset 0",
    "speed": "100 km/h",
    "target_x": -0.007,
    "target_y": 0.989,
    "target_z": -19.785,
    "mitt_x": -0.2,
    "mitt_y": 1.04,
    "mitt_z": -19.706,
    "catch_result": "Strike"
  },
  {
    "dataset": "Dataset 0",
    "speed": "100 km/h",
    "target_x": -0.012,
    "target_y": 1.003,
    "target_z": -19.756,
    "mitt_x": -0.251,
    "mitt_y": 0.85,
    "mitt_z": -19.723,
    "catch_result": "Strike"
  },
  {
    "dataset": "Dataset 0",
    "speed": "100 km/h",
    "target_x": -0.025,
    "target_y": 0.99,
    "target_z": -19.71,
    "mitt_x": -0.33,
    "mitt_y": 0.975,
    "mitt_z": -19.709,
    "catch_result": "Strike"
  },
  {
    "dataset": "Dataset 0",
    "speed": "100 km/h",
    "target_x": -0.018,
    "target_y": 0.982,
    "target_z": -19.744,
    "mitt_x": -0.262,
    "mitt_y": 1.004,
    "mitt_z": -19.756,
    "catch_result": "Strike"
  },
  {
    "dataset": "Dataset 0",
    "speed": "100 km/h",
    "target_x": -0.015,
    "target_y": 1.009,
    "target_z": -19.736,
    "mitt_x": 0.15,
    "mitt_y": 0.965,
    "mitt_z": -19.713,
    "catch_result": "Strike"
  },
  {
    "dataset": "Dataset 0",
    "speed": "100 km/h",
    "target_x": -0.019,
    "target_y": 0.999,
    "target_z": -19.702,
    "mitt_x": 0.156,
    "mitt_y": 1.115,
    "mitt_z": -19.652,
    "catch_result": "Strike"
  },
  {
    "dataset": "Dataset 0",
    "speed": "158 km/h",
    "target_x": -0.009,
    "target_y": 1.008,
    "target_z": -19.732,
    "mitt_x": 0.134,
    "mitt_y": 0.874,
    "mitt_z": -19.707,
    "catch_result": "Strike"
  },
  {
    "dataset": "Dataset 0",
    "speed": "158 km/h",
    "target_x": 0.0,
    "target_y": 1.037,
    "target_z": -19.723,
    "mitt_x": -0.011,
    "mitt_y": 0.838,
    "mitt_z": -19.692,
    "catch_result": "Strike"
  },
  {
    "dataset": "Dataset 0",
    "speed": "158 km/h",
    "target_x": -0.013,
    "target_y": 1.052,
    "target_z": -19.694,
    "mitt_x": 0.183,
    "mitt_y": 0.949,
    "mitt_z": -19.669,
    "catch_result": "Strike"
  },
  {
    "dataset": "Dataset 0",
    "speed": "158 km/h",
    "target_x": -0.033,
    "target_y": 1.026,
    "target_z": -19.7,
    "mitt_x": 0.064,
    "mitt_y": 0.839,
    "mitt_z": -19.716,
    "catch_result": "Strike"
  },
  {
    "dataset": "Dataset 0",
    "speed": "158 km/h",
    "target_x": -0.009,
    "target_y": 1.044,
    "target_z": -19.692,
    "mitt_x": 0.086,
    "mitt_y": 0.799,
    "mitt_z": -19.916,
    "catch_result": "Strike_PassedBall"
  },
  {
    "dataset": "Dataset 0",
    "speed": "158 km/h",
    "target_x": 0.017,
    "target_y": 1.042,
    "target_z": -19.709,
    "mitt_x": 0.238,
    "mitt_y": 1.008,
    "mitt_z": -20.01,
    "catch_result": "Strike_PassedBall"
  },
  {
    "dataset": "Dataset 0",
    "speed": "158 km/h",
    "target_x": 0.006,
    "target_y": 1.041,
    "target_z": -19.766,
    "mitt_x": 0.085,
    "mitt_y": 0.938,
    "mitt_z": -19.676,
    "catch_result": "Strike"
  },
  {
    "dataset": "Dataset 0",
    "speed": "158 km/h",
    "target_x": -0.047,
    "target_y": 1.019,
    "target_z": -19.69,
    "mitt_x": -0.044,
    "mitt_y": 1.076,
    "mitt_z": -19.699,
    "catch_result": "Strike_PassedBall"
  },
  {
    "dataset": "Dataset 0",
    "speed": "158 km/h",
    "target_x": -0.025,
    "target_y": 1.023,
    "target_z": -19.676,
    "mitt_x": -0.297,
    "mitt_y": 1.062,
    "mitt_z": -19.674,
    "catch_result": "Strike_PassedBall"
  },
  {
    "dataset": "Dataset 0",
    "speed": "158 km/h",
    "target_x": -0.013,
    "target_y": 1.025,
    "target_z": -19.624,
    "mitt_x": 0.036,
    "mitt_y": 1.145,
    "mitt_z": -19.617,
    "catch_result": "Strike"
  },
  {
    "dataset": "Dataset 0",
    "speed": "158 km/h",
    "target_x": 0.02,
    "target_y": 0.985,
    "target_z": -19.701,
    "mitt_x": 0.059,
    "mitt_y": 0.902,
    "mitt_z": -19.657,
    "catch_result": "Strike"
  },
  {
    "dataset": "Dataset 0",
    "speed": "158 km/h",
    "target_x": -0.047,
    "target_y": 1.026,
    "target_z": -19.672,
    "mitt_x": -0.082,
    "mitt_y": 0.945,
    "mitt_z": -19.697,
    "catch_result": "Strike"
  },
  {
    "dataset": "Dataset 0",
    "speed": "158 km/h",
    "target_x": 0.015,
    "target_y": 1.061,
    "target_z": -19.675,
    "mitt_x": -0.218,
    "mitt_y": 1.059,
    "mitt_z": -19.703,
    "catch_result": "Strike"
  },
  {
    "dataset": "Dataset 0",
    "speed": "158 km/h",
    "target_x": 0.019,
    "target_y": 1.027,
    "target_z": -19.694,
    "mitt_x": -0.248,
    "mitt_y": 1.122,
    "mitt_z": -19.722,
    "catch_result": "Strike"
  },
  {
    "dataset": "Dataset 0",
    "speed": "158 km/h",
    "target_x": 0.015,
    "target_y": 0.971,
    "target_z": -19.712,
    "mitt_x": 0.07,
    "mitt_y": 0.976,
    "mitt_z": -19.704,
    "catch_result": "Strike"
  },
  {
    "dataset": "Dataset 0",
    "speed": "158 km/h",
    "target_x": -0.007,
    "target_y": 0.993,
    "target_z": -19.767,
    "mitt_x": -0.132,
    "mitt_y": 0.719,
    "mitt_z": -19.917,
    "catch_result": "Strike_PassedBall"
  },
  {
    "dataset": "Dataset 0",
    "speed": "158 km/h",
    "target_x": -0.005,
    "target_y": 1.038,
    "target_z": -19.764,
    "mitt_x": -0.152,
    "mitt_y": 1.03,
    "mitt_z": -19.753,
    "catch_result": "Strike"
  },
  {
    "dataset": "Dataset 0",
    "speed": "158 km/h",
    "target_x": 0.001,
    "target_y": 0.986,
    "target_z": -19.749,
    "mitt_x": -0.144,
    "mitt_y": 0.943,
    "mitt_z": -19.639,
    "catch_result": "Strike"
  },
  {
    "dataset": "Dataset 2",
    "speed": "100 km/h",
    "target_x": -0.028,
    "target_y": 0.854,
    "target_z": -19.749,
    "mitt_x": -0.021,
    "mitt_y": 0.859,
    "mitt_z": -19.753,
    "catch_result": "Strike"
  },
  {
    "dataset": "Dataset 2",
    "speed": "100 km/h",
    "target_x": -0.094,
    "target_y": 0.88,
    "target_z": -19.738,
    "mitt_x": -0.118,
    "mitt_y": 0.893,
    "mitt_z": -19.696,
    "catch_result": "Strike_PassedBall"
  },
  {
    "dataset": "Dataset 2",
    "speed": "100 km/h",
    "target_x": -0.064,
    "target_y": 1.043,
    "target_z": -19.724,
    "mitt_x": 0.003,
    "mitt_y": 1.044,
    "mitt_z": -19.732,
    "catch_result": "Strike"
  },
  {
    "dataset": "Dataset 2",
    "speed": "100 km/h",
    "target_x": -0.045,
    "target_y": 1.168,
    "target_z": -19.734,
    "mitt_x": -0.025,
    "mitt_y": 1.19,
    "mitt_z": -19.724,
    "catch_result": "Ball_PassedBall"
  },
  {
    "dataset": "Dataset 2",
    "speed": "100 km/h",
    "target_x": -0.045,
    "target_y": 1.077,
    "target_z": -19.723,
    "mitt_x": -0.031,
    "mitt_y": 1.073,
    "mitt_z": -19.721,
    "catch_result": "Strike"
  },
  {
    "dataset": "Dataset 2",
    "speed": "100 km/h",
    "target_x": -0.039,
    "target_y": 1.104,
    "target_z": -19.72,
    "mitt_x": -0.002,
    "mitt_y": 1.123,
    "mitt_z": -19.723,
    "catch_result": "Strike"
  },
  {
    "dataset": "Dataset 2",
    "speed": "100 km/h",
    "target_x": 0.139,
    "target_y": 0.889,
    "target_z": -19.721,
    "mitt_x": 0.176,
    "mitt_y": 0.889,
    "mitt_z": -19.704,
    "catch_result": "Ball_PassedBall"
  },
  {
    "dataset": "Dataset 2",
    "speed": "100 km/h",
    "target_x": 0.085,
    "target_y": 0.895,
    "target_z": -19.725,
    "mitt_x": -0.018,
    "mitt_y": 0.872,
    "mitt_z": -19.687,
    "catch_result": "Strike"
  },
  {
    "dataset": "Dataset 2",
    "speed": "100 km/h",
    "target_x": 0.04,
    "target_y": 0.883,
    "target_z": -19.73,
    "mitt_x": 0.096,
    "mitt_y": 0.888,
    "mitt_z": -19.715,
    "catch_result": "Strike_PassedBall"
  },
  {
    "dataset": "Dataset 2",
    "speed": "100 km/h",
    "target_x": -0.003,
    "target_y": 0.878,
    "target_z": -19.728,
    "mitt_x": -0.063,
    "mitt_y": 0.881,
    "mitt_z": -19.717,
    "catch_result": "Strike"
  },
  {
    "dataset": "Dataset 2",
    "speed": "100 km/h",
    "target_x": 0.095,
    "target_y": 0.882,
    "target_z": -19.744,
    "mitt_x": -0.026,
    "mitt_y": 0.886,
    "mitt_z": -19.717,
    "catch_result": "Strike"
  },
  {
    "dataset": "Dataset 1",
    "speed": "158 km/h",
    "target_x": -0.025,
    "target_y": 0.949,
    "target_z": -19.594,
    "mitt_x": -0.029,
    "mitt_y": 0.862,
    "mitt_z": -19.506,
    "catch_result": "Strike"
  },
  {
    "dataset": "Dataset 1",
    "speed": "158 km/h",
    "target_x": -0.028,
    "target_y": 0.926,
    "target_z": -19.574,
    "mitt_x": -0.011,
    "mitt_y": 0.853,
    "mitt_z": -19.535,
    "catch_result": "Strike"
  },
  {
    "dataset": "Dataset 1",
    "speed": "158 km/h",
    "target_x": -0.028,
    "target_y": 0.875,
    "target_z": -19.567,
    "mitt_x": -0.035,
    "mitt_y": 0.79,
    "mitt_z": -19.527,
    "catch_result": "Strike"
  },
  {
    "dataset": "Dataset 1",
    "speed": "158 km/h",
    "target_x": -0.033,
    "target_y": 0.867,
    "target_z": -19.57,
    "mitt_x": 0.207,
    "mitt_y": 0.851,
    "mitt_z": -19.645,
    "catch_result": "Ball_WildPitch"
  },
  {
    "dataset": "Dataset 1",
    "speed": "158 km/h",
    "target_x": -0.021,
    "target_y": 0.842,
    "target_z": -19.602,
    "mitt_x": -0.045,
    "mitt_y": 0.78,
    "mitt_z": -19.539,
    "catch_result": "Strike"
  },
  {
    "dataset": "Dataset 1",
    "speed": "158 km/h",
    "target_x": -0.032,
    "target_y": 0.852,
    "target_z": -19.591,
    "mitt_x": -0.044,
    "mitt_y": 0.743,
    "mitt_z": -19.556,
    "catch_result": "Strike"
  },
  {
    "dataset": "Dataset 1",
    "speed": "158 km/h",
    "target_x": -0.038,
    "target_y": 0.828,
    "target_z": -19.575,
    "mitt_x": -0.023,
    "mitt_y": 0.783,
    "mitt_z": -19.527,
    "catch_result": "Strike"
  },
  {
    "dataset": "Dataset 1",
    "speed": "158 km/h",
    "target_x": -0.034,
    "target_y": 0.823,
    "target_z": -19.567,
    "mitt_x": -0.067,
    "mitt_y": 0.737,
    "mitt_z": -19.517,
    "catch_result": "Strike"
  },
  {
    "dataset": "Dataset 1",
    "speed": "158 km/h",
    "target_x": -0.032,
    "target_y": 0.833,
    "target_z": -19.574,
    "mitt_x": -0.025,
    "mitt_y": 0.684,
    "mitt_z": -19.501,
    "catch_result": "Strike"
  },
  {
    "dataset": "Dataset 1",
    "speed": "158 km/h",
    "target_x": -0.032,
    "target_y": 0.844,
    "target_z": -19.567,
    "mitt_x": -0.037,
    "mitt_y": 0.802,
    "mitt_z": -19.543,
    "catch_result": "Strike"
  },
  {
    "dataset": "Dataset 3",
    "speed": "100 km/h",
    "target_x": 0.029,
    "target_y": 0.468,
    "target_z": -19.829,
    "mitt_x": -0.13,
    "mitt_y": 0.507,
    "mitt_z": -19.754,
    "catch_result": "Strike"
  },
  {
    "dataset": "Dataset 3",
    "speed": "100 km/h",
    "target_x": -0.036,
    "target_y": 0.762,
    "target_z": -19.831,
    "mitt_x": -0.035,
    "mitt_y": 0.854,
    "mitt_z": -19.771,
    "catch_result": "Strike"
  },
  {
    "dataset": "Dataset 3",
    "speed": "100 km/h",
    "target_x": 0.011,
    "target_y": 0.754,
    "target_z": -19.861,
    "mitt_x": 0.013,
    "mitt_y": 0.788,
    "mitt_z": -19.824,
    "catch_result": "Strike_PassedBall"
  },
  {
    "dataset": "Dataset 3",
    "speed": "100 km/h",
    "target_x": 0.047,
    "target_y": 0.747,
    "target_z": -19.887,
    "mitt_x": -0.067,
    "mitt_y": 0.569,
    "mitt_z": -19.696,
    "catch_result": "Strike_PassedBall"
  },
  {
    "dataset": "Dataset 3",
    "speed": "100 km/h",
    "target_x": -0.047,
    "target_y": 0.773,
    "target_z": -19.86,
    "mitt_x": -0.209,
    "mitt_y": 0.725,
    "mitt_z": -19.72,
    "catch_result": "Strike"
  },
  {
    "dataset": "Dataset 3",
    "speed": "100 km/h",
    "target_x": -0.036,
    "target_y": 0.762,
    "target_z": -19.846,
    "mitt_x": 0.065,
    "mitt_y": 0.722,
    "mitt_z": -19.757,
    "catch_result": "Strike"
  },
  {
    "dataset": "Dataset 3",
    "speed": "100 km/h",
    "target_x": -0.044,
    "target_y": 0.715,
    "target_z": -19.825,
    "mitt_x": 0.113,
    "mitt_y": 0.76,
    "mitt_z": -19.733,
    "catch_result": "Strike"
  },
  {
    "dataset": "Dataset 3",
    "speed": "100 km/h",
    "target_x": -0.041,
    "target_y": 0.684,
    "target_z": -19.863,
    "mitt_x": 0.119,
    "mitt_y": 0.701,
    "mitt_z": -19.751,
    "catch_result": "Strike_PassedBall"
  },
  {
    "dataset": "Dataset 3",
    "speed": "100 km/h",
    "target_x": 0.087,
    "target_y": 0.739,
    "target_z": -19.917,
    "mitt_x": 0.032,
    "mitt_y": 0.473,
    "mitt_z": -19.754,
    "catch_result": "Ball_PassedBall"
  },
  {
    "dataset": "Dataset 3",
    "speed": "100 km/h",
    "target_x": -0.014,
    "target_y": 0.692,
    "target_z": -19.874,
    "mitt_x": 0.105,
    "mitt_y": 0.455,
    "mitt_z": -19.716,
    "catch_result": "Ball_PassedBall"
  },
  {
    "dataset": "Dataset 3",
    "speed": "100 km/h",
    "target_x": 0.011,
    "target_y": 0.751,
    "target_z": -19.86,
    "mitt_x": 0.007,
    "mitt_y": 0.419,
    "mitt_z": -19.648,
    "catch_result": "Strike_PassedBall"
  }
]